CHANGELOG.md
LICENSE
MANIFEST.in
README.md
setup.py
remarkable/__init__.py
remarkable/__main__.py
remarkable/cli.py
remarkable/util.py
remarkable.egg-info/PKG-INFO
remarkable.egg-info/SOURCES.txt
remarkable.egg-info/dependency_links.txt
remarkable.egg-info/entry_points.txt
remarkable.egg-info/requires.txt
remarkable.egg-info/top_level.txt
remarkable/templates/remark/index.html
remarkable/templates/remark/css/Droid-Serif.css
remarkable/templates/remark/css/Yanone-Kaffeesatz.css
remarkable/templates/remark/js/remark-0.5.5.min.js
remarkable/templates/remark/js/remark-0.5.6.min.js
remarkable/templates/reveal/index.html
remarkable/templates/reveal/css/reveal.css
remarkable/templates/reveal/css/reveal.min.css
remarkable/templates/reveal/css/print/paper.css
remarkable/templates/reveal/css/print/pdf.css
remarkable/templates/reveal/css/theme/README.md
remarkable/templates/reveal/css/theme/beige.css
remarkable/templates/reveal/css/theme/default.css
remarkable/templates/reveal/css/theme/moon.css
remarkable/templates/reveal/css/theme/night.css
remarkable/templates/reveal/css/theme/serif.css
remarkable/templates/reveal/css/theme/simple.css
remarkable/templates/reveal/css/theme/sky.css
remarkable/templates/reveal/css/theme/solarized.css
remarkable/templates/reveal/css/theme/source/beige.scss
remarkable/templates/reveal/css/theme/source/default.scss
remarkable/templates/reveal/css/theme/source/moon.scss
remarkable/templates/reveal/css/theme/source/night.scss
remarkable/templates/reveal/css/theme/source/serif.scss
remarkable/templates/reveal/css/theme/source/simple.scss
remarkable/templates/reveal/css/theme/source/sky.scss
remarkable/templates/reveal/css/theme/source/solarized.scss
remarkable/templates/reveal/css/theme/template/mixins.scss
remarkable/templates/reveal/css/theme/template/settings.scss
remarkable/templates/reveal/css/theme/template/theme.scss
remarkable/templates/reveal/js/notes-server.js
remarkable/templates/reveal/js/notes.js
remarkable/templates/reveal/js/reveal.js
remarkable/templates/reveal/js/reveal.min.js
remarkable/templates/reveal/js/zoom.js