Metadata-Version: 1.0
Name: remarkable
Version: 0.3.1
Summary: remarkable
Home-page: https://github.com/michaeljoseph/remarkable
Author: Michael Joseph
Author-email: michaeljoseph@gmail.com
License: Apache License
